python_anvil/__init__.py
python_anvil/api.py
python_anvil/api_resources/__init__.py
python_anvil/api_resources/base.py
python_anvil/api_resources/mutations/__init__.py
python_anvil/api_resources/mutations/base.py
python_anvil/api_resources/mutations/create_etch_packet.py
python_anvil/api_resources/mutations/forge_submit.py
python_anvil/api_resources/mutations/generate_etch_signing_url.py
python_anvil/api_resources/mutations/helpers.py
python_anvil/api_resources/payload.py
python_anvil/api_resources/requests.py
python_anvil/cli.py
python_anvil/constants.py
python_anvil/exceptions.py
python_anvil/http.py
python_anvil/models.py
python_anvil/py.typed
python_anvil/tests/__init__.py
python_anvil/tests/conftest.py
python_anvil/tests/payloads.py
python_anvil/tests/test_api.py
python_anvil/tests/test_cli.py
python_anvil/tests/test_http.py
python_anvil/tests/test_models.py
python_anvil/tests/test_utils.py
python_anvil/utils.py
python_anvil-5.1.2.dist-info/LICENSE.md
python_anvil-5.1.2.dist-info/METADATA
python_anvil-5.1.2.dist-info/WHEEL
python_anvil-5.1.2.dist-info/entry_points.txt
python_anvil-5.1.2.dist-info/RECORD
