Metadata-Version: 2.3
Name: python_anvil
Version: 5.1.2
Summary: Anvil API
License: MIT
Keywords: anvil,api,pdf,signing
Author: Anvil Foundry Inc.
Author-email: developers@useanvil.com
Requires-Python: >=3.8.0,<3.14
Classifier: Development Status :: 3 - Alpha
Classifier: License :: OSI Approved :: MIT License
Classifier: Natural Language :: English
Classifier: Operating System :: OS Independent
Classifier: Programming Language :: Python
Classifier: Programming Language :: Python :: 3
Classifier: Programming Language :: Python :: 3.8
Classifier: Programming Language :: Python :: 3.9
Classifier: Programming Language :: Python :: 3.10
Classifier: Programming Language :: Python :: 3.11
Classifier: Programming Language :: Python :: 3.12
Classifier: Programming Language :: Python :: 3.13
Classifier: Topic :: Software Development :: Libraries :: Python Modules
Requires-Dist: click (>=8.0,<9.0)
Requires-Dist: gql[requests] (==3.6.0b2)
Requires-Dist: pydantic (>=2.8,<3.0)
Requires-Dist: ratelimit (>=2.2.1,<3.0.0)
Requires-Dist: requests (>=2.28.2,<3.0.0)
Requires-Dist: tabulate (>=0.9.0,<0.10.0)
Project-URL: Documentation, https://github.com/anvilco/python-anvil
Project-URL: Homepage, https://www.useanvil.com/
Project-URL: Repository, https://github.com/anvilco/python-anvil
